{
  "kind": "collectionType",
  "collectionName": "resources",
  "info": {
    "singularName": "resource",
    "pluralName": "resources",
    "displayName": "Resource",
    "description": ""
  },
  "options": {
    "draftAndPublish": true
  },
  "pluginOptions": {},
  "attributes": {
    "name": {
      "type": "string",
      "required": true
    },
    "link": {
      "type": "string",
      "required": true
    },
    "description": {
      "type": "richtext"
    },
    "image": {
      "type": "string"
    },
    "soft_skill": {
      "type": "relation",
      "relation": "oneToOne",
      "target": "api::soft-skill.soft-skill"
    }
  }
}
